pycolorizer.py
setup.cfg
setup.py
PyColorizer.egg-info/PKG-INFO
PyColorizer.egg-info/SOURCES.txt
PyColorizer.egg-info/dependency_links.txt
PyColorizer.egg-info/top_level.txt