Metadata-Version: 1.0
Name: PyColorizer
Version: 0.1
Summary: Add color in your shell
Home-page: https://github.com/PierreRambaud/color
Author: Pierre Rambaud (GoT)
Author-email: pierre.rambaud86@gmail.com
License: GPLv3
Platform: UNKNOWN
